README.rst
setup.py
ticking.py
ticking.egg-info/PKG-INFO
ticking.egg-info/SOURCES.txt
ticking.egg-info/dependency_links.txt
ticking.egg-info/top_level.txt