Metadata-Version: 1.1
Name: ticking
Version: 0.3.0
Summary: A small timing utility library, handling framerates and rough benchmarks.
Home-page: https://github.com/mbr/ticking
Author: Marc Brinkmann
Author-email: git@marcbrinkmann.de
License: MIT
Platform: UNKNOWN
Classifier: Programming Language :: Python :: 2
Classifier: Programming Language :: Python :: 3
